[
  {
    "id": "mmooh6xub9evzqrs9wa",
    "cantante": "Carlos",
    "cancion": "Despacito",
    "mesa": "3",
    "estado": "esperando",
    "timestamp": 1773393122658
  },
  {
    "id": "mmoohowsbuxdtr4ndd",
    "cantante": "Maria",
    "cancion": "Felices los 4",
    "mesa": "7",
    "estado": "esperando",
    "timestamp": 1773393145948
  },
  {
    "id": "mmoohowwtwa4slhneok",
    "cantante": "Pedro",
    "cancion": "La Bamba",
    "mesa": "3",
    "estado": "esperando",
    "timestamp": 1773393145952
  }
]